milagro_bls_binding-1.9.0.dist-info/METADATA
milagro_bls_binding-1.9.0.dist-info/WHEEL
milagro_bls_binding-1.9.0.dist-info/license_files/LICENSE
milagro_bls_binding/__init__.py
milagro_bls_binding/milagro_bls_binding.abi3.so
milagro_bls_binding-1.9.0.dist-info/RECORD
