Metadata-Version: 2.1
Name: milagro-bls-binding
Version: 1.9.0
Classifier: Development Status :: 3 - Alpha
Classifier: Intended Audience :: Developers
Classifier: License :: OSI Approved :: MIT License
Classifier: Natural Language :: English
Classifier: Programming Language :: Python :: 3.7
Requires-Dist: pytest>=6.2.5; extra == 'test'
Requires-Dist: pytest-benchmark>=3.2.3; extra == 'test'
Requires-Dist: py-ecc==6.0.0; extra == 'test'
Provides-Extra: test
License-File: LICENSE
Author: chihchengliang@gmail.com
Author-email: chihchengliang@gmail.com
Maintainer: Chih-Cheng Liang
Maintainer-email: chihchengliang@gmail.com
Requires-Python: >=3.7
Project-URL: Source, https://github.com/ChihChengLiang/milagro_bls_binding/
